gissue/__init__.py
gissue/auth.py
gissue/gissue.py
gissue/issue.py
gissue-0.4.dist-info/LICENSE
gissue-0.4.dist-info/METADATA
gissue-0.4.dist-info/WHEEL
gissue-0.4.dist-info/top_level.txt
gissue-0.4.dist-info/RECORD
