Metadata-Version: 2.1
Name: gissue
Version: 0.4
Summary: Command line tool for managing GitHub project issues.
Home-page: http://github.com/sam-lane/gissue
Author: Sam Lane
Author-email: gissue@samlane.io
License: MIT
Platform: UNKNOWN
Requires-Dist: Requests (==2.21.0)
Requires-Dist: Colr (==0.8.3)
